nbs_social_auth/__init__.py
nbs_social_auth/base.py
nbs_social_auth/google.py
nbs_social_auth-0.1.2.dist-info/METADATA
nbs_social_auth-0.1.2.dist-info/WHEEL
nbs_social_auth-0.1.2.dist-info/RECORD
