Metadata-Version: 2.1
Name: nbs-social-auth
Version: 0.1.2
Summary: A no BS auth package to add google login to your Restful APIs
License: MIT
Author: Gupta-Anubhav12
Requires-Python: >=3.7,<4.0
Classifier: License :: OSI Approved :: MIT License
Classifier: Programming Language :: Python :: 3
Classifier: Programming Language :: Python :: 3.7
Classifier: Programming Language :: Python :: 3.8
Classifier: Programming Language :: Python :: 3.9
Classifier: Programming Language :: Python :: 3.10
Classifier: Programming Language :: Python :: 3.11
Requires-Dist: requests (>=2.31.0,<3.0.0)
Project-URL: Documentation, https://github.com/Gupta-Anubhav12/nbs-social-auth/blob/main/README.md
